{
  "bars": [
    {
      "name": "Python",
      "level": 92
    },
    {
      "name": "Reinforcement Learning",
      "level": 90
    },
    {
      "name": "Deep Learning ",
      "level": 90
    },
    {
      "name": "Computer Vision",
      "level": 80
    },
    {
      "name": "Motion Planning & Control",
      "level": 83
    },
    {
      "name": "ROS / Robotics Simulation",
      "level": 80
    }
  ],
  "categories": [
    {
      "label": "AI / ML Frameworks",
      "tags": [
        "PyTorch",
        "TensorFlow",
        "Scikit-Learn",
        "NumPy",
        "Pandas",
        "SciPy"
      ]
    },
    {
      "label": "Computer Vision",
      "tags": [
        "OpenCV",
        "Pillow",
        "YOLO",
        "VLMs"
      ]
    },
    {
      "label": "Robotics & Simulation",
      "tags": [
        "ROS",
        "Gazebo",
        "CARLA"
      ]
    },
    {
      "label": "Programming Languages",
      "tags": [
        "Python",
        "C / C++"
      ]
    },
    {
      "label": "Tools & Infrastructure",
      "tags": [
        "Git",
        "Docker",
        "MATLAB / Simulink"
      ]
    }
  ],
  "certifications": [
    {
      "title": "Machine Learning Specialization",
      "issuer": "Coursera & DeepLearning.AI",
      "topics": [
        "Supervised ML: Regression & Classification",
        "Advanced Learning Algorithms",
        "Unsupervised Learning, Recommenders, Reinforcement Learning"
      ]
    },
    {
      "title": "TensorFlow for AI, ML & Deep Learning",
      "issuer": "Coursera & DeepLearning.AI"
    },
    {
      "title": "Introduction to Data Science",
      "issuer": "Coursera & IBM"
    }
  ]
}
